{
  "template": "challenges",
  "typeName": "Kind",
  "gameManualTitle": "Spielanleitung",
  "gameManualText": "Mit unserer App „KÖLN AN RHEIN UND SEINE“ kannst du dein Wissen und deine Schnelligkeit testen, verborgene Dinge entdecken und an unserer Verlosung teilnehmen.\n\n# So geht‘s\nSchau' dir die ausgestellten Fotografien, Objekte und Infotexte zuerst gut an. Achte auf kleine Dinge, sie werden dir helfen, die kniffeligen Aufgaben zu lösen. Aber du hast nur 60 Sekunden Zeit! Leuchtet deine Antwort grün, hast du richtig getippt. Je schneller du richtig antwortest, umso mehr Punkte bekommst du. Die Stoppuhr startet immer erst dann, wenn du auf „Weiter“ klickst.  Du kannst dir also alles in Ruhe vorher ansehen.\n\n# Hier lang\nEine Wegbeschreibung vor jeder Frage führt dich immer genau dahin, wo die nächste Aufgabe auf dich wartet. Zwischen den einzelnen Stationen kannst du dir also auch wieder Zeit lassen.\n\n# Deine Belohnung\nZeig' am Ende deiner Reise dein Ergebnis unserem Kassenpersonal. Unter den zehn besten Spielerinnen und Spielern verlosen wir Gutscheine für unseren Museumsshop!\n\nWir wünschen dir eine spannende Reise von Köln nach Paris!",
  "resumeGameText": "Möchtest Du deinen letzten Besuch fortführen?",
  "finishTopText": "Du hast alle Stationen von\n\"KÖLN AN RHEIN UND SEINE\"\ngemeistert und bist am Ziel angekommen.",
  "finishBottomText": "Zeige deinen Punktestand an der Kasse, um am Gewinnspiel teilzunehmen."
}
