{
    "fields": [
        {
            "name": "nodeID",
            "type": "number"
        },
        {
            "name": "xPosition",
            "type": "number"
        },
        {
            "name": "yPosition",
            "type": "number"
        },
        {
            "name": "connectedTo",
            "type": "string"
        },
        {
            "name": "skin",
            "type": "string"
        },
        {
            "name": "nodeState",
            "type": "string"
        },
        {
            "name": "isStart",
            "type": "string"
        },
        {
            "name": "isExit",
            "type": "string"
        },
        {
            "name": "expectedVisitors",
            "type": "number"
        },
        {
            "name": "nodePauseTime",
            "type": "number"
        },
        {
            "name": "collisionEventNode",
            "type": "string"
        },
        {
            "name": "edgeTreshold",
            "type": "number"
        },
        {
            "name": "edgeDirection",
            "type": "string"
        },
        {
            "name": "collisionEventEdge",
            "type": "string"
        }
    ]
    
}