{
  "fields": [
    {
      "name": "logo",
      "type": "image"
    },
    {
      "name": "avatarsSmall",
      "type": "image"
    },
    {
      "name": "avatarsMedium",
      "type": "image"
    },
    {
      "name": "avatarsLarge",
      "type": "image"
    },
    {
      "name": "graphIcon",
      "type": "image"
    },
    {
      "name": "hiddenIcon",
      "type": "image"
    },
    {
      "name": "clickerIcon",
      "type": "image"
    },
    {
      "name": "quizIcon",
      "type": "image"
    },
    {
      "name": "skillIcon",
      "type": "image"
    },
    {
      "name": "astragalIcon",
      "type": "image"
    },
    {
      "name": "sortingIcon",
      "type": "image"
    },
    {
      "name": "lobbyIconWaiting",
      "type": "image"
    },
    {
      "name": "lobbyIconError",
      "type": "image"
    },
    {
      "name": "challengeSelectionRandom",
      "type": "image"
    },
    {
      "name": "dashboardRecentGamesBackground",
      "type": "image"
    },
    {
      "name": "dashboardHighscoreBackground",
      "type": "image"
    },
    {
      "name": "dashboardWingSign",
      "type": "image"
    }
  ]
}
